external_ip.py
external_ip-0.1.0.dist-info/LICENSE
external_ip-0.1.0.dist-info/METADATA
external_ip-0.1.0.dist-info/WHEEL
external_ip-0.1.0.dist-info/entry_points.txt
external_ip-0.1.0.dist-info/top_level.txt
external_ip-0.1.0.dist-info/RECORD
