Metadata-Version: 2.1
Name: external-ip
Version: 0.1.0
Summary: Query the IP address of the external network.
Home-page: https://github.com/fjwCode/external-ip
Author: White Turing
Author-email: fujiawei@stu.hznu.edu.cn
License: BSD
Keywords: ip,tool,internet
Platform: UNKNOWN
Classifier: Intended Audience :: Developers
Classifier: License :: OSI Approved :: BSD License
Classifier: Operating System :: OS Independent
Classifier: Programming Language :: Python :: 2
Classifier: Programming Language :: Python :: 3
Classifier: Programming Language :: Python :: Implementation :: CPython
Classifier: Topic :: Software Development :: Libraries :: Python Modules
Requires-Dist: requests
